<?xml version="1.0" encoding="utf-8"?>
<annotation>
<folder>images</folder>
<filename>9ff5feea-IMG_5507.jpeg</filename>
<source>
<database>MyDatabase</database>
<annotation>COCO2017</annotation>
<image>flickr</image>
<flickrid>NULL</flickrid>
<annotator>1</annotator>
</source>
<owner>
<flickrid>NULL</flickrid>
<name>Label Studio</name>
</owner>
<size>
<width>3024</width>
<height>4032</height>
<depth>3</depth>
</size>
<segmented>0</segmented>
<object>
<name>amaarae_the angel you don't know</name>
<pose>Unspecified</pose>
<truncated>0</truncated>
<difficult>0</difficult>
<bndbox>
<xmin>95</xmin>
<ymin>1936</ymin>
<xmax>1488</xmax>
<ymax>3276</ymax>
</bndbox>
</object>
<object>
<name>frank ocean_blonde</name>
<pose>Unspecified</pose>
<truncated>0</truncated>
<difficult>0</difficult>
<bndbox>
<xmin>1544</xmin>
<ymin>613</ymin>
<xmax>2865</xmax>
<ymax>1839</ymax>
</bndbox>
</object>
</annotation>
